analyst_klondike/__init__.py
analyst_klondike/analyst_klondike.py
analyst_klondike/dev_runner.py
analyst_klondike/py.typed
analyst_klondike/features/app/actions.py
analyst_klondike/features/app/app_reducer.py
analyst_klondike/features/app/open_file_action.py
analyst_klondike/features/code/actions.py
analyst_klondike/features/code/code_reducer.py
analyst_klondike/features/code/selector.py
analyst_klondike/features/code/state.py
analyst_klondike/features/code/wrap_func.py
analyst_klondike/features/code/code_runner/result_case.py
analyst_klondike/features/code/code_runner/runner.py
analyst_klondike/features/code_explorer/actions.py
analyst_klondike/features/code_explorer/code_explorer_reducer.py
analyst_klondike/features/code_import/analysis/code_analysis.py
analyst_klondike/features/code_import/ui_actions/actions.py
analyst_klondike/features/code_import/ui_actions/code_import_reducer.py
analyst_klondike/features/code_import/ui_actions/import_task_from_code.py
analyst_klondike/features/code_import/ui_actions/selectors.py
analyst_klondike/features/current/actions.py
analyst_klondike/features/current/current_state.py
analyst_klondike/features/current/selectors.py
analyst_klondike/features/data_context/data_state.py
analyst_klondike/features/data_context/init_action.py
analyst_klondike/features/data_context/load_file_reducer.py
analyst_klondike/features/data_context/save_action.py
analyst_klondike/features/data_context/selectors.py
analyst_klondike/features/data_context/set_opened_file_action.py
analyst_klondike/features/data_context/arg_file_load/arg_load.py
analyst_klondike/features/data_context/json_load/dc.py
analyst_klondike/features/demo_quiz/demo.json
analyst_klondike/features/demo_quiz/demo.py
analyst_klondike/features/demo_quiz/demo.yaml
analyst_klondike/features/demo_quiz/demo_solved.yaml
analyst_klondike/features/events/api_sender.py
analyst_klondike/features/events/event_actions.py
analyst_klondike/features/events/event_hook.py
analyst_klondike-1.0.17.dist-info/METADATA
analyst_klondike-1.0.17.dist-info/WHEEL
analyst_klondike-1.0.17.dist-info/entry_points.txt
analyst_klondike-1.0.17.dist-info/licenses/LICENSE.txt
analyst_klondike-1.0.17.dist-info/RECORD
