Metadata-Version: 2.4
Name: analyst-klondike
Version: 1.0.17
Summary: Тренажер Python от Клондайка Аналитика
Author-email: Analyst Klondike <analyst-klondike@yandex.ru>
License: Commercial License
License-File: LICENSE.txt
Classifier: Development Status :: 4 - Beta
Classifier: Programming Language :: Python
Classifier: Programming Language :: Python :: 3.8
Classifier: Programming Language :: Python :: 3.9
Classifier: Programming Language :: Python :: 3.10
Classifier: Programming Language :: Python :: 3.11
Classifier: Programming Language :: Python :: 3.12
Classifier: Programming Language :: Python :: Implementation :: CPython
Classifier: Programming Language :: Python :: Implementation :: PyPy
Requires-Python: >=3.12
Requires-Dist: httpx==0.28.1
Requires-Dist: pyperclip==1.9.0
Requires-Dist: pyyaml==6.0.2
Requires-Dist: textual==6.8.0
Requires-Dist: textual[syntax]
